simple_token_bucket/__init__.py
simple_token_bucket/backends/__init__.py
simple_token_bucket/backends/redis.py
simple_token_bucket-0.2.0.dist-info/METADATA
simple_token_bucket-0.2.0.dist-info/WHEEL
simple_token_bucket-0.2.0.dist-info/licenses/LICENSE
simple_token_bucket-0.2.0.dist-info/RECORD
