Metadata-Version: 2.3
Name: simple-token-bucket
Version: 0.2.0
Project-URL: Source, https://github.com/buserbrasil/simple-token-bucket
Project-URL: Issues, https://github.com/buserbrasil/simple-token-bucket/issues
Author-email: Erle Carrara <carrara.erle@gmail.com>
License-File: LICENSE
Classifier: License :: OSI Approved :: MIT License
Classifier: Operating System :: OS Independent
Classifier: Programming Language :: Python :: 3
Requires-Python: >=3.8
Provides-Extra: redis
Requires-Dist: redis; extra == 'redis'
